[
  {
    "model": "core.user",
    "pk": "testpatient",
    "fields": {
      "username": "testpatient",
      "password": "1234",
      "first_name": "John",
      "last_name": "Lennon",
      "email": "john_lennon@gmail.com",
      "gender": "M",
      "dob": "1987-05-06",
      "age": 32,
      "address": "669D Jurong West Street 64 04-50",
      "postalcode": "644669",
      "contactnumber": "67909773"
    }
  },
  {
    "model": "core.patient",
    "pk": "testpatient",
    "fields": {}
  },
  {
    "model": "core.user",
    "pk": "testpatient2",
    "fields": {
      "username": "testpatient2",
      "password": "1234",
      "first_name": "Daniel",
      "last_name": "Hwakings",
      "email": "daniel_hawkings@gmail.com",
      "gender": "M",
      "dob": "1987-08-02",
      "age": 32,
      "address": "68 Toa Payoh Street 12",
      "postalcode": "120988",
      "contactnumber": "90192837"
    }
  },
  {
    "model": "core.patient",
    "pk": "testpatient2",
    "fields": {}
  },
  {
    "model": "core.user",
    "pk": "testhealthcare",
    "fields": {
      "username": "testhealthcare",
      "password": "1234",
      "first_name": "Johnathan",
      "last_name": "Lam",
      "email": "johnathan_lam@yahoo.com",
      "gender": "M",
      "dob": "1995-05-07",
      "age": 24,
      "address": "511 Guillemard Road #02-12 Grandlink Square",
      "postalcode": 399849,
      "contactnumber": 67449185
    }
  },
  {
    "model": "core.healthcare",
    "pk": "testhealthcare",
    "fields": {
      "license": 234567,
      "patients": [
        "testpatient",
        "testpatient2"
      ]
    }
  },
  {
    "model": "core.user",
    "pk": "testhealthcare2",
    "fields": {
      "username": "testhealthcare2",
      "password": "1234",
      "first_name": "Percy",
      "last_name": "Jackson",
      "email": "percy_jackson@hotmail.com",
      "gender": "M",
      "dob": "1987-04-02",
      "age": 32,
      "address": "148 Ang Mo Kio Avenue 2",
      "postalcode": 309826,
      "contactnumber": 91820563
    }
  },
  {
    "model": "core.healthcare",
    "pk": "testhealthcare2",
    "fields": {
      "license": 123456,
      "patients": [
        "testpatient"
      ]
    }
  },
  {
    "model": "core.user",
    "pk": "testresearcher",
    "fields": {
      "username": "testresearcher",
      "password": "1234",
      "first_name": "John",
      "last_name": "Lennon",
      "email": "john_lennon@gmail.com",
      "gender": "M",
      "dob": "1987-05-06",
      "age": 32,
      "address": "669D Jurong West Street 64 04-50",
      "postalcode": "644669",
      "contactnumber": "67909773"
    }
  },
  {
    "model": "core.researcher",
    "pk": "testresearcher",
    "fields": {}
  }
]